bing_search_mcp-0.1.0.dist-info/licenses/LICENSE
bingsearch/__init__.py
bingsearch/__main__.py
bingsearch/server.py
bing_search_mcp-0.1.0.dist-info/METADATA
bing_search_mcp-0.1.0.dist-info/WHEEL
bing_search_mcp-0.1.0.dist-info/entry_points.txt
bing_search_mcp-0.1.0.dist-info/top_level.txt
bing_search_mcp-0.1.0.dist-info/RECORD
